LICENSE
MANIFEST.in
README.md
setup.py
django_inlineobjects.egg-info/PKG-INFO
django_inlineobjects.egg-info/SOURCES.txt
django_inlineobjects.egg-info/dependency_links.txt
django_inlineobjects.egg-info/not-zip-safe
django_inlineobjects.egg-info/requires.txt
django_inlineobjects.egg-info/top_level.txt
inlines/__init__.py
inlines/admin.py
inlines/models.py
inlines/parser.py
inlines/receivers.py
inlines/settings.py
inlines/templates/inlines/inlines.js
inlines/templatetags/__init__.py
inlines/templatetags/inlines_tags.py