Metadata-Version: 1.1
Name: django-inlineobjects
Version: 2.0.0
Summary: A reusable Django application used to insert content objects into other pieces of content.
Home-page: https://github.com/pigmonkey/django-inlineobjects
Author: Peter Hogg
Author-email: peter@havenaut.net
License: UNKNOWN
Platform: UNKNOWN
Classifier: Programming Language :: Python
Classifier: License :: OSI Approved :: BSD License
Classifier: Operating System :: OS Independent
Classifier: Development Status :: 5 - Production/Stable
Classifier: Framework :: Django
